social_auth_backend_prologin/__init__.py
social_auth_backend_prologin/backend.py
social_auth_backend_prologin/pipeline.py
social_auth_backend_prologin-0.1.3.dist-info/LICENSE
social_auth_backend_prologin-0.1.3.dist-info/METADATA
social_auth_backend_prologin-0.1.3.dist-info/WHEEL
social_auth_backend_prologin-0.1.3.dist-info/top_level.txt
social_auth_backend_prologin-0.1.3.dist-info/RECORD
