Metadata-Version: 2.1
Name: social-auth-backend-prologin
Version: 0.1.3
Summary: Prologin social auth backend
Home-page: https://github.com/prologin/social-auth-backend
Author: Association Prologin
Author-email: info@prologin.org
License: UNKNOWN
Project-URL: Bug tracker, https://github.com/prologin/social-auth-backend/issues
Platform: UNKNOWN
Classifier: Development Status :: 4 - Beta
Classifier: Environment :: Plugins
Classifier: Environment :: Web Environment
Requires-Python: >=3.6
License-File: LICENSE
Requires-Dist: social-auth-app-django (==4.0.0)
Requires-Dist: python-jose (==3.3.0)
